[{"url" : "/wiki/Lithium_iron_phosphate_battery", "title" : "Lithium iron phosphate battery", "category" : "Energy (Storage)"}, 
{"url" : "/wiki/Compressed_air_energy_storage", "title" : "Compressed air energy storage", "category" : "Energy (Storage)"}, 
{"url" : "/wiki/Flywheel_energy_storage", "title" : "Flywheel energy storage", "category" : "Energy (Storage)"}, 
{"url" : "/wiki/Grid_energy_storage", "title" : "Grid energy storage", "category" : "Energy (Storage)"}, 
{"url" : "/wiki/Lithium%E2%80%93air_battery", "title" : "Lithium–air battery", "category" : "Energy (Storage)"}, 
{"url" : "/wiki/Molten-salt_battery", "title" : "Molten-salt battery", "category" : "Energy (Storage)"}, 
{"url" : "/wiki/Nanowire_battery", "title" : "Nanowire battery", "category" : "Energy (Storage)"}, 
{"url" : "/wiki/Research_in_lithium-ion_batteries", "title" : "Research in lithium-ion batteries", "category" : "Energy (Storage)"}, 
{"url" : "/wiki/Silicon%E2%80%93air_battery", "title" : "Silicon–air battery", "category" : "Energy (Storage)"}, 
{"url" : "/wiki/Thermal_energy_storage", "title" : "Thermal energy storage", "category" : "Energy (Storage)"}, 
{"url" : "/wiki/Electric_double-layer_capacitor", "title" : "Electric double-layer capacitor", "category" : "Energy (Storage)"}, 

{"url" : "/wiki/Smart_grid", "title" : "Smart grid", "category" : "Energy (Other)"}, 
{"url" : "/wiki/Wireless_power_transfer", "title" : "Wireless power transfer", "category" : "Energy (Other)"}, 

{"url" : "/wiki/Ambient_intelligence", "title" : "Ambient intelligence", "category" : "Information and Communications Technology"}, 
{"url" : "/wiki/Internet_of_things", "title" : "Internet of things", "category" : "Information and Communications Technology"}, 
{"url" : "/wiki/Artificial_intelligence", "title" : "Artificial intelligence", "category" : "Information and Communications Technology"}, 
{"url" : "/wiki/Applications_of_artificial_intelligence", "title" : "Applications of artificial intelligence", "category" : "Information and Communications Technology"}, 
{"url" : "/wiki/Progress_in_artificial_intelligence", "title" : "Progress in artificial intelligence", "category" : "Information and Communications Technology"}, 
{"url" : "/wiki/Machine_translation", "title" : "Machine translation", "category" : "Information and Communications Technology"}, 
{"url" : "/wiki/Mobile_translation", "title" : "Mobile translation", "category" : "Information and Communications Technology"}, 
{"url" : "/wiki/Machine_vision", "title" : "Machine vision", "category" : "Information and Communications Technology"}, 
{"url" : "/wiki/Semantic_Web", "title" : "Semantic Web", "category" : "Information and Communications Technology"}, 
{"url" : "/wiki/Speech_recognition", "title" : "Speech recognition", "category" : "Information and Communications Technology"}, 
{"url" : "/wiki/Atomtronics", "title" : "Atomtronics", "category" : "Information and Communications Technology"}, 
{"url" : "/wiki/Carbon_nanotube_field-effect_transistor", "title" : "Carbon nanotube field-effect transistor", "category" : "Information and Communications Technology"}, 
{"url" : "/wiki/Cybermethodology", "title" : "Cybermethodology", "category" : "Information and Communications Technology"}, 
{"url" : "/wiki/Optical_disc#Fourth-generation", "title" : "Optical disc", "category" : "Information and Communications Technology"}, 
{"url" : "/wiki/3D_optical_data_storage", "title" : "3D optical data storage", "category" : "Information and Communications Technology"}, 
{"url" : "/wiki/Holographic_data_storage", "title" : "Holographic data storage", "category" : "Information and Communications Technology"}, 
{"url" : "/wiki/General-purpose_computing_on_graphics_processing_units", "title" : "General-purpose computing on graphics processing units", "category" : "Information and Communications Technology"}, 
{"url" : "/wiki/Optical_computing", "title" : "Optical computing", "category" : "Information and Communications Technology"}, 
{"url" : "/wiki/Radio-frequency_identification", "title" : "Radio-frequency identification", "category" : "Information and Communications Technology"}, 
{"url" : "/wiki/Chipless_RFID", "title" : "Chipless RFID", "category" : "Information and Communications Technology"}, 
{"url" : "/wiki/Software-defined_radio", "title" : "Software-defined radio", "category" : "Information and Communications Technology"}, 
{"url" : "/wiki/Three-dimensional_integrated_circuit", "title" : "Three-dimensional integrated circuit", "category" : "Information and Communications Technology"}, 

{"url" : "/wiki/3D_printing", "title" : "3D printing", "category" : "Manufacturing"}, 
{"url" : "/wiki/Claytronics", "title" : "Claytronics", "category" : "Manufacturing"}, 
{"url" : "/wiki/Molecular_assembler", "title" : "Molecular assembler", "category" : "Manufacturing"}, 
{"url" : "/wiki/Utility_fog", "title" : "Utility fog", "category" : "Manufacturing"}, 


{"url" : "/wiki/Aerogel", "title" : "Aerogel", "category" : "Materials science"}, 
{"url" : "/wiki/Amorphous_metal", "title" : "Amorphous metal", "category" : "Materials science"}, 
{"url" : "/wiki/Artificial_muscle", "title" : "Artificial muscle", "category" : "Materials science"}, 
{"url" : "/wiki/Conductive_polymer", "title" : "Conductive polymer", "category" : "Materials science"}, 
{"url" : "/wiki/Femtotechnology", "title" : "Femtotechnology", "category" : "Materials science"}, 
{"url" : "/wiki/Fullerene", "title" : "Fullerene", "category" : "Materials science"}, 
{"url" : "/wiki/Graphene", "title" : "Graphene", "category" : "Materials science"}, 
{"url" : "/wiki/High-temperature_superconductivity", "title" : "High-temperature superconductivity", "category" : "Materials science"}, 
{"url" : "/wiki/Superfluidity", "title" : "Superfluidity", "category" : "Materials science"}, 
{"url" : "/wiki/Linear_acetylenic_carbon", "title" : "Linear acetylenic carbon", "category" : "Materials science"}, 
{"url" : "/wiki/Metamaterial", "title" : "Metamaterial", "category" : "Materials science"}, 
{"url" : "/wiki/Metamaterial_cloaking", "title" : "Metamaterial cloaking", "category" : "Materials science"}, 
{"url" : "/wiki/Metal_foam", "title" : "Metal foam", "category" : "Materials science"}, 
{"url" : "/wiki/Multi-function_structure", "title" : "Multi-function structure", "category" : "Materials science"}, 
{"url" : "/wiki/Nanotechnology", "title" : "Nanotechnology", "category" : "Materials science"}, 
{"url" : "/wiki/Carbon_nanotube", "title" : "Carbon nanotube", "category" : "Materials science"}, 
{"url" : "/wiki/Molecular_nanotechnology", "title" : "Molecular nanotechnology", "category" : "Materials science"}, 
{"url" : "/wiki/Nanomaterials", "title" : "Nanomaterials", "category" : "Materials science"}, 
{"url" : "/wiki/Picotechnology", "title" : "Picotechnology", "category" : "Materials science"}, 
{"url" : "/wiki/Programmable_matter", "title" : "Programmable matter", "category" : "Materials science"}, 
{"url" : "/wiki/Quantum_dot", "title" : "Quantum dot", "category" : "Materials science"}, 
{"url" : "/wiki/Silicene", "title" : "Silicene", "category" : "Materials science"}, 
{"url" : "/wiki/Superalloy", "title" : "Superalloy", "category" : "Materials science"}, 
{"url" : "/wiki/Synthetic_diamond", "title" : "Synthetic diamond", "category" : "Materials science"}, 

{"url" : "/wiki/Antimatter_weapon", "title" : "Antimatter weapon", "category" : "Military technology"}, 
{"url" : "/wiki/Caseless_ammunition", "title" : "Caseless ammunition", "category" : "Military technology"}, 
{"url" : "/wiki/Directed-energy_weapon", "title" : "Directed-energy weapon", "category" : "Military technology"}, 
{"url" : "/wiki/Laser", "title" : "Laser", "category" : "Military technology"}, 
{"url" : "/wiki/Maser", "title" : "Maser", "category" : "Military technology"}, 
{"url" : "/wiki/Particle-beam_weapon", "title" : "Particle-beam weapon", "category" : "Military technology"}, 
{"url" : "/wiki/Sonic_weapon", "title" : "Sonic weapon", "category" : "Military technology"}, 
{"url" : "/wiki/Coilgun", "title" : "Coilgun", "category" : "Military technology"}, 
{"url" : "/wiki/Railgun", "title" : "Railgun", "category" : "Military technology"}, 
{"url" : "/wiki/Plasma_weapon", "title" : "Plasma weapon", "category" : "Military technology"}, 
{"url" : "/wiki/Pure_fusion_weapon", "title" : "Pure fusion weapon", "category" : "Military technology"}, 
{"url" : "/wiki/Stealth_technology", "title" : "Stealth technology", "category" : "Military technology"}, 
{"url" : "/wiki/Vortex_ring_gun", "title" : "Vortex ring gun", "category" : "Military technology"}, 

{"url" : "/wiki/Artificial_brain", "title" : "Artificial brain", "category" : "Neuroscience"}, 
{"url" : "/wiki/Brain%E2%80%93computer_interface", "title" : "Brain–computer interface", "category" : "Neuroscience"}, 
{"url" : "/wiki/Electroencephalography", "title" : "Electroencephalography", "category" : "Neuroscience"}, 
{"url" : "/wiki/Mind_uploading", "title" : "Mind uploading", "category" : "Neuroscience"}, 
{"url" : "/wiki/Brain-reading", "title" : "Brain-reading", "category" : "Neuroscience"}, 
{"url" : "/wiki/Neuroinformatics", "title" : "Neuroinformatics", "category" : "Neuroscience"}, 
{"url" : "/wiki/Neuroprosthetics", "title" : "Neuroprosthetics", "category" : "Neuroscience"}, 
{"url" : "/wiki/Visual_prosthesis", "title" : "Visual prosthesis", "category" : "Neuroscience"}, 
{"url" : "/wiki/Brain_implant", "title" : "Brain implant", "category" : "Neuroscience"}, 
{"url" : "/wiki/Exocortex", "title" : "Exocortex", "category" : "Neuroscience"}, 
{"url" : "/wiki/Retinal_implant", "title" : "Retinal implant", "category" : "Neuroscience"}, 

{"url" : "/wiki/Quantum_algorithm", "title" : "Quantum algorithm", "category" : "Quantum technology"}, 
{"url" : "/wiki/Quantum_amplifier", "title" : "Quantum amplifier", "category" : "Quantum technology"}, 
{"url" : "/wiki/Quantum_bus", "title" : "Quantum bus", "category" : "Quantum technology"}, 
{"url" : "/wiki/Quantum_channel", "title" : "Quantum channel", "category" : "Quantum technology"}, 
{"url" : "/wiki/Quantum_circuit", "title" : "Quantum circuit", "category" : "Quantum technology"}, 
{"url" : "/wiki/Quantum_complexity_theory", "title" : "Quantum complexity theory", "category" : "Quantum technology"}, 
{"url" : "/wiki/Quantum_computing", "title" : "Quantum computing", "category" : "Quantum technology"}, 
{"url" : "/wiki/Quantum_cryptography", "title" : "Quantum cryptography", "category" : "Quantum technology"}, 
{"url" : "/wiki/Quantum_dynamics", "title" : "Quantum dynamics", "category" : "Quantum technology"}, 
{"url" : "/wiki/Quantum_electronics", "title" : "Quantum electronics", "category" : "Quantum technology"}, 
{"url" : "/wiki/Quantum_error_correction", "title" : "Quantum error correction", "category" : "Quantum technology"}, 
{"url" : "/wiki/Quantum_imaging", "title" : "Quantum imaging", "category" : "Quantum technology"}, 
{"url" : "/wiki/Quantum_information", "title" : "Quantum information", "category" : "Quantum technology"}, 
{"url" : "/wiki/Quantum_key_distribution", "title" : "Quantum key distribution", "category" : "Quantum technology"}, 
{"url" : "/wiki/Quantum_logic", "title" : "Quantum logic", "category" : "Quantum technology"}, 
{"url" : "/wiki/Quantum_gate", "title" : "Quantum gate", "category" : "Quantum technology"}, 
{"url" : "/wiki/Quantum_machine", "title" : "Quantum machine", "category" : "Quantum technology"}, 
{"url" : "/wiki/Quantum_machine_learning", "title" : "Quantum machine learning", "category" : "Quantum technology"}, 
{"url" : "/wiki/Quantum_metamaterial", "title" : "Quantum metamaterial", "category" : "Quantum technology"}, 
{"url" : "/wiki/Quantum_metrology", "title" : "Quantum metrology", "category" : "Quantum technology"}, 
{"url" : "/wiki/Quantum_network", "title" : "Quantum network", "category" : "Quantum technology"}, 
{"url" : "/wiki/Quantum_neural_network", "title" : "Quantum neural network", "category" : "Quantum technology"}, 
{"url" : "/wiki/Quantum_optics", "title" : "Quantum optics", "category" : "Quantum technology"}, 
{"url" : "/wiki/Quantum_programming", "title" : "Quantum programming", "category" : "Quantum technology"}, 
{"url" : "/wiki/Quantum_sensor", "title" : "Quantum sensor", "category" : "Quantum technology"}, 
{"url" : "/wiki/Quantum_simulator", "title" : "Quantum simulator", "category" : "Quantum technology"}, 
{"url" : "/wiki/Quantum_teleportation", "title" : "Quantum teleportation", "category" : "Quantum technology"}]